PricePredictionModel/__init__.py
PricePredictionModel/model.pkl
PricePredictionModel/model.py
AvocadoPricePredictionModel-0.3.7.dist-info/METADATA
AvocadoPricePredictionModel-0.3.7.dist-info/WHEEL
AvocadoPricePredictionModel-0.3.7.dist-info/top_level.txt
AvocadoPricePredictionModel-0.3.7.dist-info/RECORD
